kuafu_bot/__init__.py
kuafu_bot-0.1.0.dist-info/METADATA
kuafu_bot-0.1.0.dist-info/WHEEL
kuafu_bot-0.1.0.dist-info/top_level.txt
kuafu_bot-0.1.0.dist-info/RECORD
