Metadata-Version: 2.1
Name: kuafu-bot
Version: 0.1.0
Summary: kuafu_bot
Home-page: 
Author: kuafu
Author-email: simpxx@gmail.com
License: LICENSE
Classifier: Programming Language :: Python :: 3
Classifier: License :: OSI Approved :: MIT License
Classifier: Operating System :: OS Independent
Requires-Python: >=3.6
